lifelog/__init__.py
lifelog/__main__.py
lifelog/config.py
lifelog/crypto_utils.py
lifelog/db_handler.py
lifelog/res/icon_128.png
lifelog/res/ui.glade
Lifelog-1.0.0.dist-info/LICENSE
Lifelog-1.0.0.dist-info/METADATA
Lifelog-1.0.0.dist-info/WHEEL
Lifelog-1.0.0.dist-info/entry_points.txt
Lifelog-1.0.0.dist-info/top_level.txt
Lifelog-1.0.0.dist-info/RECORD
