Metadata-Version: 2.1
Name: Lifelog
Version: 1.0.0
Summary: A simple and secure diary app
Home-page: https://github.com/MrBeam89/lifelog/
Download-URL: https://pypi.org/project/Lifelog/
Author: MrBeam89_
Author-email: mrbeam89@protonmail.com
Maintainer: MrBeam89_
Maintainer-email: mrbeam89@protonmail.com
License: GPLv3
Classifier: Development Status :: 5 - Production/Stable
Classifier: Environment :: X11 Applications :: GTK
Classifier: Intended Audience :: End Users/Desktop
Classifier: License :: OSI Approved :: GNU General Public License v3 (GPLv3)
Classifier: Natural Language :: English
Classifier: Operating System :: POSIX :: Linux
Classifier: Programming Language :: Python :: 3.9
Classifier: Programming Language :: Python :: 3.10
Classifier: Programming Language :: Python :: 3.11
Classifier: Programming Language :: Python :: 3.12
Classifier: Programming Language :: Python :: 3.13
Classifier: Programming Language :: Python :: 3.14
Classifier: Topic :: Office/Business :: News/Diary
Requires-Python: >=3.9
License-File: LICENSE
Requires-Dist: pycryptodomex
Requires-Dist: pygobject
Requires-Dist: scrypt
Provides-Extra: dev
Requires-Dist: twine ; extra == 'dev'
